obk/__init__.py
obk/__main__.py
obk/cli.py
obk/containers.py
obk/harmonize.py
obk/preprocess.py
obk/project_path.py
obk/py.typed
obk/services.py
obk/trace_id.py
obk/validation.py
obk/application/__init__.py
obk/application/prompts/__init__.py
obk/application/prompts/ports.py
obk/application/prompts/commands/__init__.py
obk/application/prompts/commands/add_prompt.py
obk/application/prompts/queries/__init__.py
obk/application/prompts/queries/list_prompts.py
obk/domain/__init__.py
obk/domain/prompts/__init__.py
obk/domain/prompts/models.py
obk/infrastructure/__init__.py
obk/infrastructure/db/__init__.py
obk/infrastructure/db/engine.py
obk/infrastructure/db/prompts.py
obk/infrastructure/db/sqlalchemy_repo.py
obk/infrastructure/db/sqlite.py
obk/infrastructure/mediator/__init__.py
obk/infrastructure/mediator/core.py
obk/presentation/__init__.py
obk/presentation/cli/__init__.py
obk/presentation/cli/db_cmds.py
obk/presentation/cli/main.py
obk/presentation/cli/prompt_cmds.py
obk/templates/__init__.py
obk/templates/prompt.xml
obk/xsd/prompt.xsd
obk-0.10.0.dist-info/METADATA
obk-0.10.0.dist-info/WHEEL
obk-0.10.0.dist-info/entry_points.txt
obk-0.10.0.dist-info/licenses/LICENSE
obk-0.10.0.dist-info/RECORD
